dash_lottie_loading/DashLottieLoading.py
dash_lottie_loading/__init__.py
dash_lottie_loading/_imports_.py
dash_lottie_loading/async-DashLottieLoading.js
dash_lottie_loading/async-DashLottieLoading.js.map
dash_lottie_loading/dash_lottie_loading.min.js
dash_lottie_loading/dash_lottie_loading.min.js.map
dash_lottie_loading/metadata.json
dash_lottie_loading/package-info.json
dash_lottie_loading-0.0.1.dist-info/LICENSE
dash_lottie_loading-0.0.1.dist-info/METADATA
dash_lottie_loading-0.0.1.dist-info/WHEEL
dash_lottie_loading-0.0.1.dist-info/top_level.txt
dash_lottie_loading-0.0.1.dist-info/RECORD
