Metadata-Version: 2.1
Name: dash-lottie-loading
Version: 0.0.1
Summary: Project Description
Home-page: UNKNOWN
Author: Francesco Fornari <francesco.fornari.96@gmail.com>
License: MIT
Platform: UNKNOWN
Classifier: Framework :: Dash
License-File: LICENSE
